jiratimehook/__init__.py
jiratimehook/main.py
jiratimehook-0.2.1.dist-info/DESCRIPTION.rst
jiratimehook-0.2.1.dist-info/METADATA
jiratimehook-0.2.1.dist-info/RECORD
jiratimehook-0.2.1.dist-info/WHEEL
jiratimehook-0.2.1.dist-info/metadata.json
jiratimehook-0.2.1.dist-info/top_level.txt
