Metadata-Version: 2.0
Name: jiratimehook
Version: 0.2.1
Summary: UNKNOWN
Home-page: UNKNOWN
Author: UNKNOWN
Author-email: UNKNOWN
License: MIT
Platform: UNKNOWN
Requires-Dist: jira
Requires-Dist: pbr
